__init__.py
pyhazard/gmpes.py
pyhazard-1.0.1.dist-info/METADATA
pyhazard-1.0.1.dist-info/WHEEL
pyhazard-1.0.1.dist-info/licenses/LICENSE
pyhazard-1.0.1.dist-info/RECORD
