Metadata-Version: 2.1
Name: pyhazard
Version: 1.0.1
Summary: Python package for probabilistic seismic hazard analysis (PSHA)
Project-URL: Homepage, https://github.com/blyona/HAZARD
Project-URL: Bug Tracker, https://github.com/blyona/HAZARD/issues
Author-email: blyona <benjalyona@gmail.com>
License-File: LICENSE
Classifier: License :: OSI Approved :: MIT License
Classifier: Operating System :: OS Independent
Classifier: Programming Language :: Python :: 3
Requires-Python: >=3.8
